{"cameraMode":{"drawMode":0,"name":"Shaded","section":"Shading Mode"},"sceneLighting":true,"audioPlay":false,"sceneViewState":{"showFog":true,"showMaterialUpdate":false,"showSkybox":true,"showFlares":true,"showImageEffects":true,"showParticleSystems":true},"in2DMode":false,"pivot":{"x":-2.6529502868652345,"y":-21.39329719543457,"z":30.332069396972658},"rotation":{"x":-0.3207879662513733,"y":-0.005682079121470451,"z":0.0019246889278292657,"w":-0.9471321105957031},"size":57.833003997802737,"orthographic":false}